definition.py
instance.py
task.py
camundatools/__init__.py
camundatools/base_rest.py
camundatools/cmmn.py
camundatools/definition.py
camundatools/external_task.py
camundatools/instance.py
camundatools/task.py
camundatools/x-camunda_bpm.py
camundatools/x-settings.py
camundatools-0.0.1.dist-info/LICENCE
camundatools-0.0.1.dist-info/METADATA
camundatools-0.0.1.dist-info/WHEEL
camundatools-0.0.1.dist-info/entry_points.txt
camundatools-0.0.1.dist-info/top_level.txt
camundatools-0.0.1.dist-info/RECORD
