Metadata-Version: 2.1
Name: camundatools
Version: 0.0.1
Summary: A simple camunda command line tool and framework
Home-page: https://github.com/frayel/camundatools
Author: Felipe Rayel
Author-email: felipe.rayel@gmail.com
License: MIT
Keywords: camunda
Platform: UNKNOWN
Classifier: Programming Language :: Python :: 3
Classifier: License :: OSI Approved :: MIT License
Classifier: Operating System :: OS Independent
Requires-Python: >=3.7
License-File: LICENCE
Requires-Dist: requests (>=2.0.0)
